bandcamp_api/__init__.py
bandcamp_api/album.py
bandcamp_api/artist.py
bandcamp_api/bandcamp_api.py
bandcamp_api/bandcampjson.py
bandcamp_api/daily.py
bandcamp_api/genres.py
bandcamp_api/homepage.py
bandcamp_api/label.py
bandcamp_api/search.py
bandcamp_api/track.py
bandcamp_api-0.1.15.dist-info/LICENSE
bandcamp_api-0.1.15.dist-info/METADATA
bandcamp_api-0.1.15.dist-info/WHEEL
bandcamp_api-0.1.15.dist-info/top_level.txt
bandcamp_api-0.1.15.dist-info/RECORD
